pwnedpasswds/__init__.py
pwnedpasswds/pwnedpasswds.py
pwnedpasswds-0.1.0.dist-info/entry_points.txt
pwnedpasswds-0.1.0.dist-info/LICENSE
pwnedpasswds-0.1.0.dist-info/WHEEL
pwnedpasswds-0.1.0.dist-info/METADATA
pwnedpasswds-0.1.0.dist-info/RECORD
