Metadata-Version: 2.1
Name: pwnedpasswds
Version: 0.1.0
Summary: 
Home-page: https://gitlab.com/mokytis/pwnedpasswds
License: MIT
Author: Luke Spademan
Author-email: info@lukespademan.com
Requires-Python: >=3.8,<4.0
Classifier: License :: OSI Approved :: MIT License
Classifier: Programming Language :: Python :: 3
Classifier: Programming Language :: Python :: 3.8
Requires-Dist: click (>=7.0,<8.0)
Requires-Dist: requests (>=2.23.0,<3.0.0)
Project-URL: Repository, https://gitlab.com/mokytis/pwnedpasswds
